xleaf/__init__.py
xleaf/__version__.py
xleaf/parameters.py
xleaf/prosail.cpython-39-darwin.so
xleaf/samplers.py
xleaf/simulators.py
xleaf-1.0.0.dist-info/LICENSE
xleaf-1.0.0.dist-info/METADATA
xleaf-1.0.0.dist-info/WHEEL
xleaf-1.0.0.dist-info/top_level.txt
xleaf-1.0.0.dist-info/RECORD
