Metadata-Version: 2.1
Name: xleaf
Version: 1.0.0
Summary: Leaf and canopy radiative transfer modeling tools built on PROSPECT-D and SAIL
Home-page: https://github.com/earth-chris/xleaf
Author: Christopher Anderson
Author-email: cbanders@stanford.edu
License: MIT
Keywords: prospect,sail,prosail,radiative transfer modeling,simulation modeling,remote sensing,python
Platform: any
Classifier: Programming Language :: Python :: 3
Classifier: License :: OSI Approved :: MIT License
Classifier: Operating System :: OS Independent
Requires-Python: >=3.7.0
License-File: LICENSE
Requires-Dist: numpy
